oicana/__init__.py
oicana/py.typed
oicana/template.py
oicana/types.py
oicana-0.1.0a2.dist-info/METADATA
oicana-0.1.0a2.dist-info/WHEEL
oicana-0.1.0a2.dist-info/licenses/LICENSE.md
oicana-0.1.0a2.dist-info/RECORD
