Metadata-Version: 2.4
Name: oicana
Version: 0.1.0a2
Summary: PDF templating with Typst
Project-URL: Homepage, https://oicana.com
Project-URL: Repository, https://github.com/oicana/oicana
Project-URL: Documentation, https://docs.oicana.com
Author-email: Oicana <hello@oicana.com>
License: # PolyForm Noncommercial License 1.0.0
License-File: LICENSE.md
Keywords: oicana,pdf,typesetting,typst
Classifier: Development Status :: 3 - Alpha
Classifier: Intended Audience :: Developers
Classifier: Programming Language :: Python :: 3
Classifier: Programming Language :: Python :: 3.11
Classifier: Programming Language :: Python :: 3.12
Classifier: Programming Language :: Python :: 3.13
Classifier: Programming Language :: Python :: 3.14
Classifier: Topic :: Software Development :: Libraries :: Python Modules
Requires-Python: >=3.11
Requires-Dist: oicana-native>=0.1.0a2
Provides-Extra: dev
Requires-Dist: mypy>=1.0; extra == 'dev'
Requires-Dist: pytest>=7.0; extra == 'dev'
Requires-Dist: ruff>=0.1.0; extra == 'dev'
Provides-Extra: test
Requires-Dist: pytest>=7.0; extra == 'test'
